<?xml version="1.0" encoding="UTF-8" ?><TA Data><time>2020-04-17 00:33:14.199276</time><SC_T1>34.97</SC_T1><CC_T1>34.97</CC_T1><DPG_T1>34.97</DPG_T1><pCO2>40.0</pCO2><pH2O>2791.14</pH2O><Sample_weight>2.7</Sample_weight></TA Data>
<?xml version="1.0" encoding="UTF-8" ?><TA Data><time>2020-04-17 00:33:16.202398</time><SC_T1>34.97</SC_T1><CC_T1>34.97</CC_T1><DPG_T1>34.97</DPG_T1><pCO2>40.0</pCO2><pH2O>2791.17</pH2O><Sample_weight>2.7</Sample_weight></TA Data>
<?xml version="1.0" encoding="UTF-8" ?><TA Data><time>2020-04-17 00:33:18.204775</time><SC_T1>34.97</SC_T1><CC_T1>34.97</CC_T1><DPG_T1>34.97</DPG_T1><pCO2>40.0</pCO2><pH2O>2791.21</pH2O><Sample_weight>2.7</Sample_weight></TA Data>
